revolve/__init__.py
revolve/api.py
revolve/data_types.py
revolve/external.py
revolve/functions.py
revolve/llm.py
revolve/main.py
revolve/prompts.py
revolve/tools.py
revolve/utils.py
revolve/utils_git.py
revolve/workflow_generator.py
revolve/db/__init__.py
revolve/db/adapter.py
revolve/db/mongodb_adapter.py
revolve/db/postgres_adapter.py
revolve/nodes/__init__.py
revolve/nodes/check_user_request.py
revolve/nodes/generate_api.py
revolve/nodes/generate_prompt.py
revolve/nodes/process_table.py
revolve/nodes/report.py
revolve/nodes/router.py
revolve/nodes/test.py
revolve/nodes/tool_handler.py
revolve/resources/index.html
revolve/resources/assets/index-ac765696.js
revolve/source_template/api.py
revolve/source_template/cors.py
revolve/source_template/schemas.py
revolve/source_template/static.py
revolve/source_template/test_api.py
revolve/source_template/mongodb/db_utils.py
revolve/source_template/mongodb/service.py
revolve/source_template/postgres/db_utils.py
revolve/source_template/postgres/service.py
revolve/ui/App.jsx
revolve/ui/index.css
revolve/ui/index.html
revolve/ui/package.json
revolve/ui/vite.config.js
revolve/ui/dist/index.html
revolve/ui/dist/assets/index-79811946.js
revolve/ui/dist/assets/index-aa45ee70.css
revolve/ui/mock/server.py
selfrevolve-0.1.3.dist-info/METADATA
selfrevolve-0.1.3.dist-info/WHEEL
selfrevolve-0.1.3.dist-info/entry_points.txt
selfrevolve-0.1.3.dist-info/licenses/LICENSE
selfrevolve-0.1.3.dist-info/RECORD
