Metadata-Version: 2.4
Name: selfrevolve
Version: 0.1.3
Summary: A project for generating RESTful apis given a database
Project-URL: Homepage, https://github.com/self-evolving-runtimes/revolve
Project-URL: Issues, https://github.com/self-evolving-runtimes/revolve/issues
License-Expression: MIT
License-File: LICENSE
Classifier: Intended Audience :: Developers
Classifier: Intended Audience :: System Administrators
Classifier: License :: OSI Approved :: MIT License
Classifier: Programming Language :: Python :: 3
Classifier: Topic :: Database :: Front-Ends
Classifier: Topic :: Scientific/Engineering :: Artificial Intelligence
Requires-Python: >=3.11
Requires-Dist: falcon
Requires-Dist: falcon-cors>=1.1.7
Requires-Dist: ipython>=9.2.0
Requires-Dist: langchain-openai>=0.3.15
Requires-Dist: langgraph
Requires-Dist: litellm>=1.72.6.post1
Requires-Dist: loguru>=0.7.3
Requires-Dist: psycopg2-binary>=2.9.10
Requires-Dist: pymongo>=4.13.0
Requires-Dist: pytest
Requires-Dist: pytest-json-report>=1.5.0
Requires-Dist: python-dotenv
Requires-Dist: sqlparse>=0.5.3
